{
  "date": {
    "label": "Date",
    "values": [],
    "enabled": true
  },
  "level": {
    "label": "Level",
    "values": [],
    "enabled": true
  },
  "track": {
    "label": "Track",
    "values": [6640],
    "enabled": true
  },
  "track_groups": {
    "label": "Track Group",
    "values": [],
    "enabled": true
  },
  "tags": {
    "label": "Tags",
    "values": [],
    "enabled": true
  },
  "venues": {
    "label": "Venue",
    "values": [],
    "enabled": true
  },
  "event_types": {
    "label": "Event Type",
    "values": [],
    "enabled": true
  },
  "speakers": {
    "label": "Speaker",
    "values": [],
    "enabled": true
  },
  "company": {
    "label": "Company",
    "values": [],
    "enabled": false
  },
  "title": {
    "label": "Title",
    "values": [],
    "enabled": true
  }
}
